{
  "nav": {
    "home": "Home",
    "share": "Share",
    "stories": "Words & Phrases",
    "language": "Language",
    "doogi": "Doogi",
    "contact": "Contact"
  },
  "home": {
    "title": "Doogi",
    "subtitle": "A place to share cute words from children",
    "description": "When children start talking, they sometimes mix up words in cute ways. Here you can share these sweet moments with others.",
    "features": "Why Doogi?",
    "feature1": "🎯 Share Sweet Moments",
    "feature2": "💝 Record Cute Words",
    "feature3": "🤗 Connect with Other Parents",
    "feature4": "📱 Easy and Fun to Use",
    "cta": "Share a cute word or phrase"
  },

  "share": {
    "title": "Share a Word or Phrase",
    "childName": "Child's Name",
    "childNamePlaceholder": "Enter your child's name",
    "childWord": "Cute Word or Phrase",
    "childWordPlaceholder": "Enter the word or phrase your child says",
    "explanation": "Explanation",
    "explanationPlaceholder": "Explain what your child meant or what word they mixed up",
    "submit": "Share Word or Phrase",
    "submitting": "Submitting...",
    "success": "Your word or phrase has been shared successfully!",
    "error": "Please fill in all fields.",
    "validation": {
      "childName": "Please enter your child's name",
      "childWord": "Please enter the word or phrase",
      "explanation": "Please enter an explanation"
    }
  },
  "stories": {
    "title": "Cute Words & Phrases",
    "noStories": "No words or phrases have been shared yet",
    "shareYours": "What's your child's cute word?",
    "childsWord": "Child's Word"
  },
  "footer": {
    "copyright": "All rights reserved for Doogi $year©",
    "description": "A place to share cute words from children",
    "doogi": "Doogi"
  },
  "theme": {
    "light": "Light",
    "dark": "Dark",
    "cupcake": "Cupcake",
    "emerald": "Emerald"
  },
  "about": {
    "title": "About Doogi",
    "content": "Doogi is a platform where parents can share and discover cute words that children make up while learning to talk. Our mission is to create a happy community where these precious moments are preserved and shared."
  },
  "contact": {
    "title": "Contact Us",
    "name": "Name",
    "email": "Email",
    "message": "Message",
    "send": "Send Message",
    "success": "Your message has been sent successfully!",
    "error": "Please fill in all fields."
  }
}
