{
  "nav": {
    "home": "ุฎุงูู",
    "share": "ุงุดุชุฑุงฺฉโฺฏุฐุงุฑ",
    "stories": "ฺฉููุงุช ู ุฌููุงุช",
    "language": "ุฒุจุงู",
    "doogi": "ุฏูฺฏ",
    "profile": "ูพุฑููุงู",
    "login": "ูุฑูุฏ",
    "register": "ุซุจุชโูุงู",
    "logout": "ุฎุฑูุฌ"
  },
  "home": {
    "title": "ุฏูฺฏ",
    "subtitle": "ุฌุง ุจุฑุง ุงุดุชุฑุงฺฉโฺฏุฐุงุฑ ฺฉููุงุช ุจุงูุฒู ุจฺูโูุง",
    "description": "ููุช ุจฺูโูุง ุดุฑูุน ุจู ุญุฑู ุฒุฏู ูโฺฉููุฏุ ฺฏุงู ฺฉููุงุช ุฑุง ุจู ุดฺฉู ุจุงูุฒูโุง ุฌุงุจุฌุง ูโฺฏููุฏ. ุงูุฌุง ูโุชูุงูุฏ ุงู ูุญุธุงุช ุดุฑู ุฑุง ุจุง ุฏฺฏุฑุงู ุจู ุงุดุชุฑุงฺฉ ุจฺฏุฐุงุฑุฏ.",
    "features": "ฺุฑุง ุฏูฺฏุ",
    "feature1": "๐ฏ ุงุดุชุฑุงฺฉโฺฏุฐุงุฑ ูุญุธุงุช ุดุฑู",
    "feature2": "๐ ุซุจุช ฺฉููุงุช ุจุงูุฒู ุจฺูโูุง",
    "feature3": "๐ค ุงุฑุชุจุงุท ุจุง ูุงูุฏู ุฏฺฏุฑ",
    "feature4": "๐ฑ ุงุณุชูุงุฏู ุขุณุงู ู ุณุฑฺฏุฑูโฺฉููุฏู",
    "cta": "ฺฉููู ุง ุฌููู ุจุงูุฒู ุฑุง ุจู ุงุดุชุฑุงฺฉ ุจฺฏุฐุงุฑุฏ"
  },
  "auth": {
    "register": {
      "title": "ุงุฌุงุฏ ุญุณุงุจ ฺฉุงุฑุจุฑ",
      "subtitle": "ุจู ุฏูฺฏ ุจูพููุฏุฏ ุชุง ฺฉููุงุช ุจุงูุฒู ุจฺูโูุง ุฑุง ุจู ุงุดุชุฑุงฺฉ ุจฺฏุฐุงุฑุฏ ู ฺฉุดู ฺฉูุฏ",
      "firstName": "ูุงู",
      "firstNamePlaceholder": "ูุงู ุฎูุฏ ุฑุง ูุงุฑุฏ ฺฉูุฏ",
      "lastName": "ูุงู ุฎุงููุงุฏฺฏ",
      "lastNamePlaceholder": "ูุงู ุฎุงููุงุฏฺฏ ุฎูุฏ ุฑุง ูุงุฑุฏ ฺฉูุฏ",
      "email": "ุงูู",
      "emailPlaceholder": "ุขุฏุฑุณ ุงูู ุฎูุฏ ุฑุง ูุงุฑุฏ ฺฉูุฏ",
      "password": "ุฑูุฒ ุนุจูุฑ",
      "passwordPlaceholder": "ฺฉ ุฑูุฒ ุนุจูุฑ ูู ุงุฌุงุฏ ฺฉูุฏ",
      "confirmPassword": "ุชุฃุฏ ุฑูุฒ ุนุจูุฑ",
      "confirmPasswordPlaceholder": "ุฑูุฒ ุนุจูุฑ ุฎูุฏ ุฑุง ุชุฃุฏ ฺฉูุฏ",
      "agreeToTerms": "ูู ุจุง ุดุฑุงุท ุฎุฏูุงุช ู ุณุงุณุช ุญูุธ ุญุฑู ุฎุตูุต ููุงููู",
      "submit": "ุงุฌุงุฏ ุญุณุงุจ ฺฉุงุฑุจุฑ",
      "submitting": "ุฏุฑ ุญุงู ุงุฌุงุฏ ุญุณุงุจ ฺฉุงุฑุจุฑ...",
      "success": "ุญุณุงุจ ฺฉุงุฑุจุฑ ุจุง ููููุช ุงุฌุงุฏ ุดุฏ! ุจู ุฏูฺฏ ุฎูุด ุขูุฏุฏ!",
      "error": "ูุทูุงู ุชูุงู ููุฏูุง ุฑุง ุจู ุฏุฑุณุช ูพุฑ ฺฉูุฏ.",
      "alreadyHaveAccount": "ูุจูุงู ุญุณุงุจ ฺฉุงุฑุจุฑ ุฏุงุฑุฏุ",
      "loginLink": "ุงูุฌุง ูุงุฑุฏ ุดูุฏ",
      "validation": {
        "firstName": "ูุทูุงู ูุงู ุฎูุฏ ุฑุง ูุงุฑุฏ ฺฉูุฏ",
        "lastName": "ูุทูุงู ูุงู ุฎุงููุงุฏฺฏ ุฎูุฏ ุฑุง ูุงุฑุฏ ฺฉูุฏ",
        "email": "ูุทูุงู ฺฉ ุขุฏุฑุณ ุงูู ูุนุชุจุฑ ูุงุฑุฏ ฺฉูุฏ",
        "password": "ุฑูุฒ ุนุจูุฑ ุจุงุฏ ุญุฏุงูู ธ ฺฉุงุฑุงฺฉุชุฑ ุจุงุดุฏ",
        "confirmPassword": "ุฑูุฒูุง ุนุจูุฑ ูุทุงุจูุช ูุฏุงุฑูุฏ",
        "terms": "ุดูุง ุจุงุฏ ุจุง ุดุฑุงุท ู ููุงูู ููุงููุช ฺฉูุฏ"
      }
    },
    "login": {
      "title": "ูุฑูุฏ",
      "subtitle": "ุฎูุด ุขูุฏุฏ! ูุทูุงู ุจุฑุง ุงุฏุงูู ูุงุฑุฏ ุดูุฏ.",
      "email": "ุงูู",
      "emailPlaceholder": "ุขุฏุฑุณ ุงูู ุฎูุฏ ุฑุง ูุงุฑุฏ ฺฉูุฏ",
      "password": "ุฑูุฒ ุนุจูุฑ",
      "passwordPlaceholder": "ุฑูุฒ ุนุจูุฑ ุฎูุฏ ุฑุง ูุงุฑุฏ ฺฉูุฏ",
      "submit": "ูุฑูุฏ",
      "submitting": "ุฏุฑ ุญุงู ูุฑูุฏ...",
      "error": "ูุทูุงู ุงูู ู ุฑูุฒ ุนุจูุฑ ุฑุง ูุงุฑุฏ ฺฉูุฏ."
    }
  },
  "share": {
    "title": "ุงุดุชุฑุงฺฉโฺฏุฐุงุฑ ฺฉููู ุง ุฌููู",
    "childName": "ูุงู ูุฑุฒูุฏ",
    "childNamePlaceholder": "ูุงู ูุฑุฒูุฏ ุฎูุฏ ุฑุง ูุงุฑุฏ ฺฉูุฏ",
    "childWord": "ฺฉููู ุง ุฌููู ุจุงูุฒู",
    "childWordPlaceholder": "ฺฉููู ุง ุฌูููโุง ฺฉู ูุฑุฒูุฏุชุงู ูโฺฏูุฏ ุฑุง ูุงุฑุฏ ฺฉูุฏ",
    "explanation": "ุชูุถุญุงุช",
    "explanationPlaceholder": "ุชูุถุญ ุฏูุฏ ฺฉู ูุฑุฒูุฏุชุงู ฺู ููุธูุฑ ุฏุงุดุชู ุง ฺู ฺฉูููโุง ุฑุง ุงุดุชุจุงู ฺฏูุชู ุงุณุช",
    "submit": "ุซุจุช ฺฉููู ุง ุฌููู",
    "submitting": "ุฏุฑ ุญุงู ุซุจุช...",
    "success": "ฺฉููู ุง ุฌููู ุดูุง ุจุง ููููุช ุซุจุช ุดุฏ!",
    "error": "ูุทูุงู ุชูุงู ููุฏูุง ุฑุง ูพุฑ ฺฉูุฏ.",
    "validation": {
      "childName": "ูุทูุงู ูุงู ูุฑุฒูุฏ ุฑุง ูุงุฑุฏ ฺฉูุฏ",
      "childWord": "ูุทูุงู ฺฉููู ุง ุฌููู ุฑุง ูุงุฑุฏ ฺฉูุฏ",
      "explanation": "ูุทูุงู ุชูุถุญุงุช ุฑุง ูุงุฑุฏ ฺฉูุฏ"
    }
  },
  "stories": {
    "title": "ฺฉููุงุช ู ุฌููุงุช ุจุงูุฒู",
    "noStories": "ูููุฒ ฺฉููู ุง ุฌูููโุง ุซุจุช ูุดุฏู ุงุณุช",
    "shareYours": "ฺฉููู ุจุงูุฒู ูุฑุฒูุฏ ุดูุง ฺ ูุณุชุ",
    "childsWord": "ฺฉููู ุจุงูุฒู ูุฑุฒูุฏ"
  },
  "footer": {
    "copyright": "ุชูุงู ุญููู ุจุฑุง ุฏูฺฏ ูุญููุธ ุงุณุช $yearยฉ",
    "description": "ุฌุง ุจุฑุง ุงุดุชุฑุงฺฉโฺฏุฐุงุฑ ฺฉููุงุช ุจุงูุฒู ุจฺูโูุง",
    "doogi": "ุฏูฺฏ"
  },
  "theme": {
    "light": "ุฑูุดู",
    "dark": "ุชุฑู",
    "cupcake": "ฺฉุงูพโฺฉฺฉ",
    "emerald": "ุฒูุฑุฏ"
  },
  "about": {
    "title": "ุฏุฑุจุงุฑู ุฏูฺฏ",
    "content": "ุฏูฺฏ ูพูุชูุฑู ุงุณุช ฺฉู ูุงูุฏู ูโุชูุงููุฏ ุฏุฑ ุขู ฺฉููุงุช ุจุงูุฒูโุง ฺฉู ุจฺูโูุง ููฺฏุงู ุงุฏฺฏุฑ ุตุญุจุช ฺฉุฑุฏู ูโุณุงุฒูุฏ ุฑุง ุจู ุงุดุชุฑุงฺฉ ุจฺฏุฐุงุฑูุฏ ู ฺฉุดู ฺฉููุฏ. ูุงููุฑุช ูุง ุงุฌุงุฏ ฺฉ ุฌุงูุนู ุดุงุฏ ุงุณุช ฺฉู ุฏุฑ ุขู ุงู ูุญุธุงุช ฺฏุฑุงูุจูุง ุญูุธ ู ุจู ุงุดุชุฑุงฺฉ ฺฏุฐุงุดุชู ุดููุฏ."
  },
  "contact": {
    "title": "ุชูุงุณ ุจุง ูุง",
    "name": "ูุงู",
    "email": "ุงูู",
    "message": "ูพุงู",
    "send": "ุงุฑุณุงู ูพุงู",
    "success": "ูพุงู ุดูุง ุจุง ููููุช ุงุฑุณุงู ุดุฏ!",
    "error": "ูุทูุงู ุชูุงู ููุฏูุง ุฑุง ูพุฑ ฺฉูุฏ."
  }
}
