{
  "nav": {
    "home": "ุฎุงูู",
    "about": "ุฏุฑุจุงุฑู ูุง",
    "contact": "ุชูุงุณ",
    "language": "ุฒุจุงู"
  },
  "home": {
    "title": "ุจู ุจุฑูุงูู ฺูุฏ ุฒุจุงูู ูุง ุฎูุด ุขูุฏุฏ",
    "subtitle": "ุณุงุฎุชู ุดุฏู ุจุง Next.js 15ุ Tailwind 4ุ ู DaisyUI 5",
    "description": "ุงู ฺฉ ููููู ุงุฒ ุจุฑูุงูู ฺูุฏ ุฒุจุงูู ุงุณุช ฺฉู ุงุฒ ุฒุจุงูโูุง ุงูฺฏูุณ ู ูุงุฑุณ ุจุง ุชฺฉููููฺโูุง ูุฏุฑู ูุจ ูพุดุชุจุงู ูโฺฉูุฏ.",
    "features": "ูฺฺฏโูุง",
    "feature1": "๐ ูพุดุชุจุงู ฺูุฏ ุฒุจุงูู (ุงูฺฏูุณ ู ูุงุฑุณ)",
    "feature2": "๐จ ุฑุงุจุท ฺฉุงุฑุจุฑ ุฒุจุง ุจุง ฺฉุงููพูููุชโูุง DaisyUI",
    "feature3": "โก ุนููฺฉุฑุฏ ุณุฑุน ุจุง Next.js 15",
    "feature4": "๐ฏ ุทุฑุงุญ ุฑุณูพุงูุณู ุจุง Tailwind CSS",
    "cta": "ุดุฑูุน ฺฉูุฏ"
  },
  "about": {
    "title": "ุฏุฑุจุงุฑู ูุง",
    "content": "ูุง ุชูุณุนูโุฏููุฏฺฏุงู ุนูุงููโููุฏ ูุณุชู ฺฉู ุจุฑูุงููโูุง ูุจ ูุฏุฑู ุจุง ุฌุฏุฏุชุฑู ุชฺฉููููฺโูุง ูโุณุงุฒู. ุชูุฑฺฉุฒ ูุง ุจุฑ ุฑู ุณุงุฎุช ุชุฌุฑุจุงุช ฺฉุงุฑุจุฑ ูพุณูุฏ ู ฺูุฏ ุฒุจุงูู ุงุณุช ฺฉู ุจู ุทูุฑ ฺฉูพุงุฑฺู ุฏุฑ ูุฑููฺฏโูุง ู ุฒุจุงูโูุง ูุฎุชูู ฺฉุงุฑ ูโฺฉููุฏ."
  },
  "contact": {
    "title": "ุชูุงุณ ุจุง ูุง",
    "name": "ูุงู",
    "email": "ุงูู",
    "message": "ูพุงู",
    "send": "ุงุฑุณุงู ูพุงู",
    "success": "ูพุงู ุจุง ููููุช ุงุฑุณุงู ุดุฏ!",
    "error": "ูุทูุงู ุชูุงู ููุฏูุง ุฑุง ูพุฑ ฺฉูุฏ."
  },
  "footer": {
    "copyright": "ยฉ ฑดฐณ ุจุฑูุงูู ฺูุฏ ุฒุจุงูู. ุชูุงู ุญููู ูุญููุธ ุงุณุช.",
    "description": "ฺฉ ุจุฑูุงูู ูุจ ฺูุฏ ุฒุจุงูู ูุฏุฑู"
  },
  "theme": {
    "light": "ุฑูุดู",
    "dark": "ุชุฑู",
    "cupcake": "ฺฉุงูพโฺฉฺฉ",
    "emerald": "ุฒูุฑุฏ"
  }
}